MANIFEST.in
README.md
requirements.txt
setup.py
cascadium/__init__.py
cascadium/__main__.py
cascadium/api.py
cascadium/atx.py
cascadium/auth.py
cascadium/environ.py
cascadium/shell.py
cascadium/solutions.py
cascadium/views.py
cascadium/viewutils.py
cascadium.egg-info/PKG-INFO
cascadium.egg-info/SOURCES.txt
cascadium.egg-info/dependency_links.txt
cascadium.egg-info/entry_points.txt
cascadium.egg-info/not-zip-safe
cascadium.egg-info/requires.txt
cascadium.egg-info/top_level.txt
cascadium/templates/login.html
cascadium/templates/upload.html